alibabacloud_cs20151215/__init__.py
alibabacloud_cs20151215/client.py
alibabacloud_cs20151215/models/__init__.py
alibabacloud_cs20151215/models/_addon.py
alibabacloud_cs20151215/models/_attach_instances_request.py
alibabacloud_cs20151215/models/_attach_instances_response.py
alibabacloud_cs20151215/models/_attach_instances_response_body.py
alibabacloud_cs20151215/models/_attach_instances_to_node_pool_request.py
alibabacloud_cs20151215/models/_attach_instances_to_node_pool_response.py
alibabacloud_cs20151215/models/_attach_instances_to_node_pool_response_body.py
alibabacloud_cs20151215/models/_cancel_cluster_upgrade_response.py
alibabacloud_cs20151215/models/_cancel_component_upgrade_response.py
alibabacloud_cs20151215/models/_cancel_operation_plan_response.py
alibabacloud_cs20151215/models/_cancel_operation_plan_response_body.py
alibabacloud_cs20151215/models/_cancel_task_response.py
alibabacloud_cs20151215/models/_check_control_plane_log_enable_response.py
alibabacloud_cs20151215/models/_check_control_plane_log_enable_response_body.py
alibabacloud_cs20151215/models/_check_service_role_request.py
alibabacloud_cs20151215/models/_check_service_role_response.py
alibabacloud_cs20151215/models/_check_service_role_response_body.py
alibabacloud_cs20151215/models/_clean_cluster_user_permissions_request.py
alibabacloud_cs20151215/models/_clean_cluster_user_permissions_response.py
alibabacloud_cs20151215/models/_clean_user_permissions_request.py
alibabacloud_cs20151215/models/_clean_user_permissions_response.py
alibabacloud_cs20151215/models/_clean_user_permissions_response_body.py
alibabacloud_cs20151215/models/_clean_user_permissions_shrink_request.py
alibabacloud_cs20151215/models/_containerd_config.py
alibabacloud_cs20151215/models/_create_auto_repair_policy_request.py
alibabacloud_cs20151215/models/_create_auto_repair_policy_response.py
alibabacloud_cs20151215/models/_create_auto_repair_policy_response_body.py
alibabacloud_cs20151215-6.5.2.dist-info/LICENSE
alibabacloud_cs20151215-6.5.2.dist-info/METADATA
alibabacloud_cs20151215-6.5.2.dist-info/WHEEL
alibabacloud_cs20151215-6.5.2.dist-info/top_level.txt
alibabacloud_cs20151215-6.5.2.dist-info/RECORD
